openstudiobackporter/__init__.py
openstudiobackporter/__main__.py
openstudiobackporter/backport_3_10_0_to_3_9_0.py
openstudiobackporter/backport_3_11_0_to_3_10_0.py
openstudiobackporter/backport_3_9_0_to_3_8_0.py
openstudiobackporter/backporter.py
openstudiobackporter/helpers.py
openstudiobackporter/main.py
openstudio_backporter-0.1.7.dist-info/METADATA
openstudio_backporter-0.1.7.dist-info/WHEEL
openstudio_backporter-0.1.7.dist-info/licenses/LICENSE
openstudio_backporter-0.1.7.dist-info/RECORD
