Metadata-Version: 2.4
Name: openstudio-backporter
Version: 0.1.7
Summary: A small library to backport an OpenStudio OSM model to an older version.
License: MIT
License-File: LICENSE
Author: Julien Marrec
Author-email: contact@effibem.com
Requires-Python: >=3.10,<4.0
Classifier: Development Status :: 2 - Pre-Alpha
Classifier: Intended Audience :: Developers
Classifier: License :: OSI Approved :: MIT License
Classifier: Natural Language :: English
Classifier: Programming Language :: Python :: 3
Classifier: Programming Language :: Python :: 3.10
Classifier: Programming Language :: Python :: 3.11
Classifier: Programming Language :: Python :: 3.12
Classifier: Programming Language :: Python :: 3.13
Classifier: Programming Language :: Python :: 3.14
Provides-Extra: test
Requires-Dist: loguru (>=0.7.3,<0.8.0)
Requires-Dist: openstudio (>=3.11.0)
Requires-Dist: pytest (>=9.0.2,<10.0.0) ; extra == "test"
Requires-Dist: pytest-cov (>=7.0.0,<8.0.0) ; extra == "test"
Project-URL: Changelog, https://github.com/jmarrec/openstudio-backporter/blob/main/CHANGELOG.md
Project-URL: Documentation, https://jmarrec.github.io/openstudio-backporter
Project-URL: Homepage, https://effibem.com
Project-URL: Issues, https://github.com/jmarrec/openstudio-backporter/issues
Project-URL: Repository, https://github.com/jmarrec/openstudio-backporter
